nimc/Main.py
nimc/__init__.py
nimc/extension.py
nimc-1.3.1.dist-info/METADATA
nimc-1.3.1.dist-info/WHEEL
nimc-1.3.1.dist-info/entry_points.txt
nimc-1.3.1.dist-info/top_level.txt
nimc-1.3.1.dist-info/RECORD
